citadelml/__init__.py
citadelml/main.py
CitadelML-1.0.5.dist-info/LICENSE
CitadelML-1.0.5.dist-info/METADATA
CitadelML-1.0.5.dist-info/WHEEL
CitadelML-1.0.5.dist-info/top_level.txt
CitadelML-1.0.5.dist-info/RECORD
