Metadata-Version: 2.1
Name: CitadelML
Version: 1.0.5
Summary: Upload and train machine learning models on a remote server.
Home-page: https://github.com/UMass-Rescue/PhotoAnalysisServer
Author: Cody Richter
Author-email: cody@richter.codes
License: UNKNOWN
Platform: UNKNOWN
Classifier: Programming Language :: Python :: 3
Classifier: License :: OSI Approved :: MIT License
Classifier: Operating System :: OS Independent
Requires-Python: >=3.0
Requires-Dist: requests
